.gitignore
LICENSE
LICENSE.txt
MANIFEST.in
README.md
setup.cfg
setup.py
test.cc
./.gitignore
./LICENSE
./LICENSE.txt
./MANIFEST.in
./README.md
./a.out
./setup.cfg
./setup.py
./test.cc
./.git/COMMIT_EDITMSG
./.git/FETCH_HEAD
./.git/HEAD
./.git/ORIG_HEAD
./.git/config
./.git/description
./.git/index
./.git/packed-refs
./.git/hooks/applypatch-msg.sample
./.git/hooks/commit-msg.sample
./.git/hooks/fsmonitor-watchman.sample
./.git/hooks/post-update.sample
./.git/hooks/pre-applypatch.sample
./.git/hooks/pre-commit.sample
./.git/hooks/pre-push.sample
./.git/hooks/pre-rebase.sample
./.git/hooks/pre-receive.sample
./.git/hooks/prepare-commit-msg.sample
./.git/hooks/update.sample
./.git/info/exclude
./.git/logs/HEAD
./.git/logs/refs/heads/master
./.git/logs/refs/heads/ml/remove_named_argument_enforce
./.git/logs/refs/remotes/origin/HEAD
./.git/logs/refs/remotes/origin/master
./.git/logs/refs/remotes/origin/ml/remove_named_argument_enforce
./.git/objects/07/79be4f50be9ddf0b3763ca83169583205d3c3a
./.git/objects/0e/006d2e0fbe0baea563ac6f3b9494f02ff67d12
./.git/objects/13/e36a13a13e7db7ee9f23a1abc06bf3c851be78
./.git/objects/1d/3b98dc4d76655b2f9813d3768aa4b907805010
./.git/objects/1f/6723ecc2d1d7e9bc179e36ab664b6e2344e025
./.git/objects/21/f4a0b3851fc06decbb26c69f7c10cbd7e59d90
./.git/objects/23/4b38463262d9cad6d62a2b88eda7be2d3a54d3
./.git/objects/25/fc40155661ed7abfa44b4c7822d8695e99ee58
./.git/objects/26/1eeb9e9f8b2b4b0d119366dda99c6fd7d35c64
./.git/objects/26/70d611b382fe91ae60c8e851abb6b2f9fa0e5b
./.git/objects/32/398e55981820e6dc529654bbf2967589864189
./.git/objects/32/42b7115fac9d004b61a45c45fae24640877258
./.git/objects/36/d9e8100d1a40862f172bbb53a023f8d5e97ff3
./.git/objects/3a/20a5fdd8caba1da60101a23ea4c80f2b496a59
./.git/objects/3a/eab0d485a05f501459922d4c5f110529e08403
./.git/objects/3b/a890e32efa4e4d0b638674c5ca4334d5c9a539
./.git/objects/3d/d84aad7559cf78b5d62ced037e39777d73f4e7
./.git/objects/45/fe2fbb9a48699145ccd8da6bd7bcec2a7603a2
./gradient_decode_dicom.egg-info/PKG-INFO
./gradient_decode_dicom.egg-info/SOURCES.txt
./gradient_decode_dicom.egg-info/dependency_links.txt
./gradient_decode_dicom.egg-info/not-zip-safe
./gradient_decode_dicom.egg-info/requires.txt
./gradient_decode_dicom.egg-info/top_level.txt
gradient_decode_dicom.egg-info/PKG-INFO
gradient_decode_dicom.egg-info/SOURCES.txt
gradient_decode_dicom.egg-info/dependency_links.txt
gradient_decode_dicom.egg-info/not-zip-safe
gradient_decode_dicom.egg-info/requires.txt
gradient_decode_dicom.egg-info/top_level.txt
