Metadata-Version: 2.1
Name: gradient-decode-dicom
Version: 0.0.5
Summary: Gradient Decode DICOM is a dicom image and tag reader op for TensorFlow
Home-page: https://github.com/gradienthealth/gradient_decode_dicom
Author: Marcelo Lerendegui
Author-email: marcelo@gradienthealth.io
License: Apache 2.0
Keywords: tensorflow dicom custom op machine learning
Platform: UNKNOWN
Classifier: Development Status :: 4 - Beta
Classifier: Intended Audience :: Developers
Classifier: Intended Audience :: Education
Classifier: Intended Audience :: Science/Research
Classifier: License :: OSI Approved :: Apache Software License
Classifier: Programming Language :: Python :: 2.7
Classifier: Programming Language :: Python :: 3.4
Classifier: Programming Language :: Python :: 3.5
Classifier: Programming Language :: Python :: 3.6
Classifier: Topic :: Scientific/Engineering :: Mathematics
Classifier: Topic :: Software Development :: Libraries :: Python Modules
Classifier: Topic :: Software Development :: Libraries
